MANIFEST.in
README.rst
setup.cfg
setup.py
ravenpackapi/__init__.py
ravenpackapi/check_connection.py
ravenpackapi/core.py
ravenpackapi/exceptions.py
ravenpackapi/util.py
ravenpackapi/version.py
ravenpackapi.egg-info/PKG-INFO
ravenpackapi.egg-info/SOURCES.txt
ravenpackapi.egg-info/dependency_links.txt
ravenpackapi.egg-info/requires.txt
ravenpackapi.egg-info/top_level.txt
ravenpackapi/examples/__init__.py
ravenpackapi/examples/copy_dataset.py
ravenpackapi/examples/create_dataset.py
ravenpackapi/examples/create_dataset_edge.py
ravenpackapi/examples/delete_dataset.py
ravenpackapi/examples/edge_entity_reference_filtered.py
ravenpackapi/examples/entity_reference_get_sedols.py
ravenpackapi/examples/get_datafile_chunked.py
ravenpackapi/examples/get_document_url.py
ravenpackapi/examples/get_historical_flat_files.py
ravenpackapi/examples/get_realtime_news.py
ravenpackapi/examples/get_top_daily_events.py
ravenpackapi/examples/indicator_datasets.py
ravenpackapi/examples/list_jobs.py
ravenpackapi/examples/multiple_daily_downloads.py
ravenpackapi/examples/perform_keyword_search.py
ravenpackapi/examples/periodic_download.py
ravenpackapi/examples/query_datafile_rollup.py
ravenpackapi/examples/query_entity_mapping.py
ravenpackapi/examples/query_entity_reference.py
ravenpackapi/examples/query_entity_types_reference.py
ravenpackapi/examples/query_with_json.py
ravenpackapi/examples/ravenpack_annotations_batch.py
ravenpackapi/examples/ravenpack_annotations_example.py
ravenpackapi/key_events/__init__.py
ravenpackapi/key_events/module.py
ravenpackapi/models/__init__.py
ravenpackapi/models/dataset.py
ravenpackapi/models/dataset_list.py
ravenpackapi/models/fields.py
ravenpackapi/models/job.py
ravenpackapi/models/mapping.py
ravenpackapi/models/reference.py
ravenpackapi/models/results.py
ravenpackapi/tests/README.md
ravenpackapi/tests/__init__.py
ravenpackapi/tests/acceptance/__init__.py
ravenpackapi/tests/acceptance/test_adhoc_json.py
ravenpackapi/tests/acceptance/test_count.py
ravenpackapi/tests/acceptance/test_datafile.py
ravenpackapi/tests/acceptance/test_dataset_crud.py
ravenpackapi/tests/acceptance/test_dataset_json.py
