Metadata-Version: 2.1
Name: ravenpackapi
Version: 1.1.5
Summary: RavenPack API - Python client
Home-page: https://github.com/RavenPack/python-api
Author: RavenPack
Author-email: dataservices@ravenpack.com
License: MIT
Keywords: python analytics api rest news data
Classifier: Development Status :: 5 - Production/Stable
Classifier: Intended Audience :: Developers
Classifier: Topic :: System :: Software Distribution
Classifier: License :: OSI Approved :: MIT License
